{"charts":{"Beginner":{"level":6,"combo":130,"bpmDisplay":"68.000–274.000","bpmMin":274.809,"bpmMax":274.311,"events":[{"t":0,"c":0,"b":274.809},{"t":4,"c":0,"b":273.889},{"t":38,"c":0,"n":"0100"},{"t":40,"c":1,"n":"1001"},{"t":42,"c":2,"n":"1000"},{"t":44,"c":3,"n":"0100"},{"t":46,"c":4,"n":"1001"},{"t":49,"c":5,"n":"0001"},{"t":52,"c":6,"n":"0010"},{"t":54,"c":7,"b":68.702},{"t":54,"c":7,"n":"1000"},{"t":56,"c":8,"b":136.709},{"t":58,"c":8,"n":"0001"},{"t":61,"c":9,"n":"0001"},{"t":62,"c":10,"b":274.025},{"t":64,"c":10,"n":"0001"},{"t":67,"c":11,"n":"0100"},{"t":69,"c":12,"n":"1000"},{"t":71,"c":13,"n":"1000"},{"t":73,"c":14,"n":"0010"},{"t":75,"c":15,"n":"0001"},{"t":77,"c":16,"n":"1001"},{"t":80,"c":17,"n":"0110"},{"t":83,"c":18,"n":"0100"},{"t":85,"c":19,"n":"0010"},{"t":87,"c":20,"n":"0010"},{"t":89,"c":21,"n":"0001"},{"t":92,"c":22,"n":"0010"},{"t":94,"c":23,"n":"1000"},{"t":97,"c":24,"n":"1000"},{"t":99,"c":25,"n":"0001"},{"t":102,"c":26,"n":"0001"},{"t":105,"c":27,"n":"0001"},{"t":108,"c":28,"n":"1000"},{"t":110,"c":29,"n":"0010"},{"t":112,"c":30,"n":"1001"},{"t":114,"c":31,"n":"0001"},{"t":116,"c":32,"n":"1001"},{"t":118,"c":33,"n":"0010"},{"t":121,"c":34,"n":"0110"},{"t":124,"c":35,"n":"0001"},{"t":126,"c":36,"n":"0010"},{"t":127,"c":37,"n":"0010"},{"t":134,"c":38,"n":"0100"},{"t":136,"c":39,"n":"1001"},{"t":140,"c":40,"n":"0100"},{"t":142,"c":41,"n":"0100"},{"t":149,"c":42,"n":"0010"},{"t":151,"c":43,"n":"1001"},{"t":154,"c":44,"n":"0100"},{"t":156,"c":45,"n":"1001"},{"t":158,"c":46,"n":"0001"},{"t":160,"c":47,"n":"0010"},{"t":163,"c":48,"n":"0010"},{"t":165,"c":49,"n":"0001"},{"t":167,"c":50,"n":"0001"},{"t":169,"c":51,"n":"0100"},{"t":171,"c":52,"n":"1000"},{"t":173,"c":53,"n":"1001"},{"t":176,"c":54,"n":"0110"},{"t":179,"c":55,"n":"0010"},{"t":181,"c":56,"n":"0100"},{"t":183,"c":57,"n":"0100"},{"t":185,"c":58,"n":"1000"},{"t":188,"c":59,"n":"0001"},{"t":190,"c":60,"n":"0110"},{"t":192,"c":61,"n":"1001"},{"t":194,"c":62,"n":"0110"},{"t":196,"c":63,"n":"1001"},{"t":198,"c":64,"n":"1000"},{"t":201,"c":65,"n":"0100"},{"t":204,"c":66,"n":"0100"},{"t":206,"c":67,"n":"1000"},{"t":208,"c":68,"n":"0010"},{"t":210,"c":69,"n":"0001"},{"t":212,"c":70,"n":"0100"},{"t":214,"c":71,"n":"0010"},{"t":217,"c":72,"n":"0001"},{"t":220,"c":73,"n":"0010"},{"t":222,"c":74,"b":75.419},{"t":222,"c":74,"n":"1000"},{"t":224,"c":75,"n":"0001"},{"t":226,"c":76,"n":"1000"},{"t":228,"c":77,"n":"0100"},{"t":230,"c":78,"n":"0100"},{"t":232,"c":79,"n":"0100"},{"t":234,"c":80,"b":78.603},{"t":234,"c":80,"n":"0010"},{"t":236,"c":81,"b":128.878},{"t":236,"c":81,"n":"0100"},{"t":240,"c":82,"n":"1000"},{"t":242,"c":83,"b":168.75},{"t":244,"c":83,"n":"0001"},{"t":248,"c":84,"b":216.867},{"t":252,"c":84,"b":274.047},{"t":252,"c":84,"n":"0010"},{"t":254,"c":85,"n":"0001"},{"t":257,"c":86,"n":"0100"},{"t":259,"c":87,"n":"1000"},{"t":261,"c":88,"n":"1000"},{"t":263,"c":89,"n":"0010"},{"t":265,"c":90,"n":"0001"},{"t":267,"c":91,"n":"1001"},{"t":270,"c":92,"n":"0110"},{"t":276,"c":93,"n":"0010"},{"t":278,"c":94,"n":"1000"},{"t":280,"c":95,"n":"0110"},{"t":282,"c":96,"n":"1001"},{"t":284,"c":97,"n":"1000"},{"t":288,"c":98,"n":"0001"},{"t":292,"c":99,"n":"0010"},{"t":296,"c":100,"n":"0010"},{"t":300,"c":101,"n":"1000"},{"t":302,"c":102,"n":"1001"},{"t":304,"c":103,"n":"0001"},{"t":306,"c":104,"n":"1001"},{"t":308,"c":105,"n":"1000"},{"t":310,"c":106,"n":"1000"},{"t":312,"c":107,"n":"1000"},{"t":314,"c":108,"n":"1000"},{"t":316,"c":109,"n":"1000"},{"t":318,"c":110,"n":"1000"},{"t":320,"c":111,"n":"1000"},{"t":322,"c":112,"n":"1000"},{"t":324,"c":113,"n":"0100"},{"t":326,"c":114,"n":"0100"},{"t":328,"c":115,"n":"0100"},{"t":330,"c":116,"n":"0100"},{"t":332,"c":117,"n":"1000"},{"t":334,"c":118,"n":"1000"},{"t":336,"c":119,"n":"1000"},{"t":338,"c":120,"n":"1000"},{"t":340,"c":121,"n":"1000"},{"t":342,"c":122,"n":"1000"},{"t":344,"c":123,"n":"0010"},{"t":346,"c":124,"n":"0010"},{"t":348,"c":125,"n":"0010"},{"t":350,"c":126,"n":"0010"},{"t":352,"c":127,"n":"0010"},{"t":354,"c":128,"n":"0100"},{"t":358,"c":129,"n":"1001"},{"t":359,"c":130,"b":274.311}],"bpms":[{"t":0,"c":0,"b":274.809},{"t":4,"c":0,"b":273.889},{"t":54,"c":7,"b":68.702},{"t":56,"c":8,"b":136.709},{"t":62,"c":10,"b":274.025},{"t":222,"c":74,"b":75.419},{"t":234,"c":80,"b":78.603},{"t":236,"c":81,"b":128.878},{"t":242,"c":83,"b":168.75},{"t":248,"c":84,"b":216.867},{"t":252,"c":84,"b":274.047},{"t":359,"c":130,"b":274.311}],"stops":[]},"Basic":{"level":10,"combo":203,"bpmDisplay":"68.000–274.000","bpmMin":274.809,"bpmMax":274.311,"events":[{"t":0,"c":0,"b":274.809},{"t":4,"c":0,"b":273.889},{"t":38,"c":0,"n":"0100"},{"t":40,"c":1,"n":"1001"},{"t":42,"c":2,"n":"1000"},{"t":44,"c":3,"n":"0100"},{"t":46,"c":4,"n":"1001"},{"t":49,"c":5,"n":"0001"},{"t":50,"c":6,"n":"1000"},{"t":52,"c":7,"n":"0010"},{"t":54,"c":8,"b":68.702},{"t":54,"c":8,"n":"1200"},{"t":55.5,"c":9,"n":"0001"},{"t":56,"c":10,"b":136.709},{"t":56.5,"c":10,"n":"1000"},{"t":58,"c":11,"n":"0001"},{"t":59.5,"c":12,"n":"1000"},{"t":61,"c":13,"n":"0301"},{"t":62,"c":14,"b":274.025},{"t":62,"c":14,"n":"1010"},{"t":64,"c":15,"n":"0101"},{"t":67,"c":16,"n":"0100"},{"t":68,"c":17,"n":"0010"},{"t":69,"c":18,"n":"1000"},{"t":71,"c":19,"n":"1000"},{"t":72,"c":20,"n":"0001"},{"t":73,"c":21,"n":"0010"},{"t":75,"c":22,"n":"0001"},{"t":77,"c":23,"n":"1001"},{"t":78,"c":24,"n":"0100"},{"t":80,"c":25,"n":"0110"},{"t":83,"c":26,"n":"0100"},{"t":84,"c":27,"n":"0001"},{"t":85,"c":28,"n":"0010"},{"t":87,"c":29,"n":"0010"},{"t":88,"c":30,"n":"1000"},{"t":89,"c":31,"n":"0001"},{"t":90,"c":32,"n":"0100"},{"t":92,"c":33,"n":"1010"},{"t":94,"c":34,"n":"1000"},{"t":97,"c":35,"n":"1000"},{"t":99,"c":36,"n":"0001"},{"t":100,"c":37,"n":"1001"},{"t":102,"c":38,"n":"0001"},{"t":105,"c":39,"n":"0001"},{"t":108,"c":40,"n":"1000"},{"t":109,"c":41,"n":"1001"},{"t":110,"c":42,"n":"1010"},{"t":112,"c":43,"n":"1001"},{"t":114,"c":44,"n":"0101"},{"t":116,"c":45,"n":"1001"},{"t":118,"c":46,"n":"0010"},{"t":121,"c":47,"n":"0110"},{"t":124,"c":48,"n":"0001"},{"t":125,"c":49,"n":"1001"},{"t":126,"c":50,"n":"0010"},{"t":127,"c":51,"n":"1010"},{"t":129.5,"c":52,"n":"1000"},{"t":130.5,"c":53,"n":"1100"},{"t":134,"c":54,"n":"0100"},{"t":135,"c":55,"n":"0010"},{"t":136,"c":56,"n":"1001"},{"t":140,"c":57,"n":"0100"},{"t":141,"c":58,"n":"0010"},{"t":142,"c":59,"n":"0011"},{"t":145.5,"c":60,"n":"0001"},{"t":146.5,"c":61,"n":"0101"},{"t":149,"c":62,"n":"1010"},{"t":151,"c":63,"n":"1001"},{"t":154,"c":64,"n":"0100"},{"t":156,"c":65,"n":"1001"},{"t":158,"c":66,"n":"0101"},{"t":160,"c":67,"n":"1010"},{"t":163,"c":68,"n":"0010"},{"t":164,"c":69,"n":"0100"},{"t":165,"c":70,"n":"0001"},{"t":167,"c":71,"n":"0001"},{"t":168,"c":72,"n":"1000"},{"t":169,"c":73,"n":"0100"},{"t":171,"c":74,"n":"1000"},{"t":173,"c":75,"n":"1001"},{"t":174,"c":76,"n":"0010"},{"t":176,"c":77,"n":"0110"},{"t":179,"c":78,"n":"0010"},{"t":180,"c":79,"n":"1000"},{"t":181,"c":80,"n":"0100"},{"t":183,"c":81,"n":"0100"},{"t":184,"c":82,"n":"0001"},{"t":185,"c":83,"n":"1000"},{"t":186,"c":84,"n":"0010"},{"t":188,"c":85,"n":"0101"},{"t":190,"c":86,"n":"0110"},{"t":192,"c":87,"n":"1001"},{"t":194,"c":88,"n":"0110"},{"t":196,"c":89,"n":"1001"},{"t":198,"c":90,"n":"1100"},{"t":199.5,"c":91,"n":"1001"},{"t":201,"c":92,"n":"0011"},{"t":202.5,"c":93,"n":"1001"},{"t":204,"c":94,"n":"0100"},{"t":205,"c":95,"n":"0110"},{"t":206,"c":96,"n":"1000"},{"t":208,"c":97,"n":"0010"},{"t":209,"c":98,"n":"1001"},{"t":210,"c":99,"n":"0001"},{"t":212,"c":100,"n":"0100"},{"t":213,"c":101,"n":"1001"},{"t":214,"c":102,"n":"1010"},{"t":215.5,"c":103,"n":"1001"},{"t":217,"c":104,"n":"0101"},{"t":218.5,"c":105,"n":"1001"},{"t":220,"c":106,"n":"0010"},{"t":221,"c":107,"n":"0110"},{"t":222,"c":108,"b":75.419},{"t":222,"c":108,"n":"1000"},{"t":223,"c":109,"n":"0100"},{"t":224,"c":110,"n":"0001"},{"t":225,"c":111,"n":"0100"},{"t":226,"c":112,"n":"1000"},{"t":227,"c":113,"n":"0001"},{"t":228,"c":114,"n":"0100"},{"t":229,"c":115,"n":"1000"},{"t":230,"c":116,"n":"0100"},{"t":231,"c":117,"n":"0001"},{"t":232,"c":118,"n":"0100"},{"t":234,"c":119,"b":78.603},{"t":234,"c":119,"n":"0010"},{"t":236,"c":120,"b":128.878},{"t":236,"c":120,"n":"0100"},{"t":240,"c":121,"n":"1000"},{"t":242,"c":122,"b":168.75},{"t":244,"c":122,"n":"0001"},{"t":248,"c":123,"b":216.867},{"t":252,"c":123,"b":274.047},{"t":252,"c":123,"n":"1010"},{"t":254,"c":124,"n":"0101"},{"t":257,"c":125,"n":"0100"},{"t":258,"c":126,"n":"0010"},{"t":259,"c":127,"n":"1000"},{"t":261,"c":128,"n":"1000"},{"t":262,"c":129,"n":"0001"},{"t":263,"c":130,"n":"0010"},{"t":265,"c":131,"n":"0001"},{"t":267,"c":132,"n":"1001"},{"t":268,"c":133,"n":"0100"},{"t":270,"c":134,"n":"0110"},{"t":273.25,"c":135,"n":"0010"},{"t":274.5,"c":136,"n":"0010"},{"t":276,"c":137,"n":"0010"},{"t":277,"c":138,"n":"0001"},{"t":278,"c":139,"n":"1000"},{"t":280,"c":140,"n":"0110"},{"t":282,"c":141,"n":"1001"},{"t":284,"c":142,"n":"1000"},{"t":285.5,"c":143,"n":"1010"},{"t":288,"c":144,"n":"0001"},{"t":289.5,"c":145,"n":"0011"},{"t":292,"c":146,"n":"0010"},{"t":293.5,"c":147,"n":"1010"},{"t":296,"c":148,"n":"0010"},{"t":297.5,"c":149,"n":"0011"},{"t":300,"c":150,"n":"1100"},{"t":302,"c":151,"n":"1001"},{"t":304,"c":152,"n":"0101"},{"t":306,"c":153,"n":"1001"},{"t":308,"c":154,"n":"1000"},{"t":309,"c":155,"n":"0100"},{"t":310,"c":156,"n":"1000"},{"t":311,"c":157,"n":"0001"},{"t":312,"c":158,"n":"1000"},{"t":313,"c":159,"n":"0010"},{"t":314,"c":160,"n":"1000"},{"t":315,"c":161,"n":"0001"},{"t":316,"c":162,"n":"1000"},{"t":317,"c":163,"n":"0010"},{"t":318,"c":164,"n":"1000"},{"t":319,"c":165,"n":"0001"},{"t":320,"c":166,"n":"1000"},{"t":321,"c":167,"n":"0100"},{"t":322,"c":168,"n":"1000"},{"t":323,"c":169,"n":"0001"},{"t":324,"c":170,"n":"0100"},{"t":325,"c":171,"n":"0010"},{"t":326,"c":172,"n":"0100"},{"t":327,"c":173,"n":"1000"},{"t":328,"c":174,"n":"0100"},{"t":329,"c":175,"n":"0010"},{"t":330,"c":176,"n":"0100"},{"t":331,"c":177,"n":"0001"},{"t":332,"c":178,"n":"1000"},{"t":333,"c":179,"n":"0100"},{"t":334,"c":180,"n":"1000"},{"t":335,"c":181,"n":"0001"},{"t":336,"c":182,"n":"1000"},{"t":337,"c":183,"n":"0100"},{"t":338,"c":184,"n":"1000"},{"t":339,"c":185,"n":"0001"},{"t":340,"c":186,"n":"1000"},{"t":341,"c":187,"n":"0010"},{"t":342,"c":188,"n":"1000"},{"t":343,"c":189,"n":"0001"},{"t":344,"c":190,"n":"0010"},{"t":345,"c":191,"n":"0100"},{"t":346,"c":192,"n":"0010"},{"t":347,"c":193,"n":"1000"},{"t":348,"c":194,"n":"0010"},{"t":349,"c":195,"n":"0100"},{"t":350,"c":196,"n":"0010"},{"t":351,"c":197,"n":"0001"},{"t":352,"c":198,"n":"0010"},{"t":353,"c":199,"n":"1000"},{"t":354,"c":200,"n":"0100"},{"t":355,"c":201,"n":"0010"},{"t":358,"c":202,"n":"2002"},{"t":359,"c":203,"b":274.311},{"t":366,"c":203,"n":"3003"}],"bpms":[{"t":0,"c":0,"b":274.809},{"t":4,"c":0,"b":273.889},{"t":54,"c":8,"b":68.702},{"t":56,"c":10,"b":136.709},{"t":62,"c":14,"b":274.025},{"t":222,"c":108,"b":75.419},{"t":234,"c":119,"b":78.603},{"t":236,"c":120,"b":128.878},{"t":242,"c":122,"b":168.75},{"t":248,"c":123,"b":216.867},{"t":252,"c":123,"b":274.047},{"t":359,"c":203,"b":274.311}],"stops":[]},"Difficult":{"level":12,"combo":259,"bpmDisplay":"68.000–274.000","bpmMin":274.809,"bpmMax":274.311,"events":[{"t":0,"c":0,"b":274.809},{"t":4,"c":0,"b":273.889},{"t":38,"c":0,"n":"0100"},{"t":40,"c":1,"n":"0010"},{"t":42,"c":2,"n":"0001"},{"t":43,"c":3,"n":"1000"},{"t":44,"c":4,"n":"0001"},{"t":46,"c":5,"n":"0110"},{"t":49,"c":6,"n":"0001"},{"t":50,"c":7,"n":"1000"},{"t":52,"c":8,"n":"0010"},{"t":54,"c":9,"b":68.702},{"t":54,"c":9,"n":"0200"},{"t":55.5,"c":10,"n":"0001"},{"t":56,"c":11,"b":136.709},{"t":56.5,"c":11,"n":"1000"},{"t":58,"c":12,"n":"0010"},{"t":59.5,"c":13,"n":"1000"},{"t":61,"c":14,"n":"0301"},{"t":62,"c":15,"b":274.025},{"t":62,"c":15,"n":"0010"},{"t":64,"c":16,"n":"0100"},{"t":66,"c":17,"n":"0001"},{"t":67,"c":18,"n":"0100"},{"t":68,"c":19,"n":"0001"},{"t":69,"c":20,"n":"1000"},{"t":71,"c":21,"n":"0100"},{"t":72,"c":22,"n":"0010"},{"t":73,"c":23,"n":"0001"},{"t":75,"c":24,"n":"1000"},{"t":77,"c":25,"n":"1000"},{"t":78,"c":26,"n":"0100"},{"t":80,"c":27,"n":"1001"},{"t":82,"c":28,"n":"0010"},{"t":83,"c":29,"n":"0001"},{"t":84,"c":30,"n":"1000"},{"t":85,"c":31,"n":"0100"},{"t":87,"c":32,"n":"0100"},{"t":88,"c":33,"n":"0010"},{"t":89,"c":34,"n":"0001"},{"t":90,"c":35,"n":"0101"},{"t":92,"c":36,"n":"1001"},{"t":94,"c":37,"n":"0010"},{"t":95,"c":38,"n":"0010"},{"t":96,"c":39,"n":"0011"},{"t":97,"c":40,"n":"0001"},{"t":98,"c":41,"n":"0001"},{"t":99,"c":42,"n":"1001"},{"t":100,"c":43,"n":"0110"},{"t":101,"c":44,"n":"0100"},{"t":102,"c":45,"n":"0010"},{"t":103,"c":46,"n":"0010"},{"t":104,"c":47,"n":"1010"},{"t":105,"c":48,"n":"1000"},{"t":106,"c":49,"n":"1000"},{"t":107,"c":50,"n":"1001"},{"t":108,"c":51,"n":"0110"},{"t":109,"c":52,"n":"0010"},{"t":110,"c":53,"n":"1000"},{"t":110.5,"c":54,"n":"0100"},{"t":112,"c":55,"n":"0010"},{"t":112.5,"c":56,"n":"0001"},{"t":114,"c":57,"n":"1000"},{"t":114.5,"c":58,"n":"0010"},{"t":116,"c":59,"n":"0100"},{"t":116.5,"c":60,"n":"0001"},{"t":118,"c":61,"n":"1010"},{"t":119.5,"c":62,"n":"1001"},{"t":121,"c":63,"n":"0101"},{"t":122.5,"c":64,"n":"0110"},{"t":124,"c":65,"n":"0010"},{"t":125,"c":66,"n":"1001"},{"t":126,"c":67,"n":"1000"},{"t":127,"c":68,"n":"0100"},{"t":129.5,"c":69,"n":"0001"},{"t":130.5,"c":70,"n":"0100"},{"t":133.5,"c":71,"n":"0010"},{"t":134,"c":72,"n":"0100"},{"t":135,"c":73,"n":"0010"},{"t":136,"c":74,"n":"1000"},{"t":137,"c":75,"n":"0010"},{"t":138,"c":76,"n":"0001"},{"t":140,"c":77,"n":"0100"},{"t":141,"c":78,"n":"0001"},{"t":142,"c":79,"n":"0100"},{"t":143,"c":80,"n":"1000"},{"t":145.5,"c":81,"n":"0100"},{"t":146.5,"c":82,"n":"0010"},{"t":149,"c":83,"n":"1000"},{"t":149.5,"c":84,"n":"0100"},{"t":150.5,"c":85,"n":"0001"},{"t":151,"c":86,"n":"0010"},{"t":152,"c":87,"n":"0001"},{"t":152.5,"c":88,"n":"1000"},{"t":154,"c":89,"n":"0100"},{"t":155,"c":90,"n":"0010"},{"t":156,"c":91,"n":"1001"},{"t":158,"c":92,"n":"0100"},{"t":160,"c":93,"n":"0010"},{"t":162,"c":94,"n":"1000"},{"t":163,"c":95,"n":"0010"},{"t":164,"c":96,"n":"1000"},{"t":165,"c":97,"n":"0001"},{"t":167,"c":98,"n":"0010"},{"t":168,"c":99,"n":"0100"},{"t":169,"c":100,"n":"1000"},{"t":171,"c":101,"n":"0001"},{"t":173,"c":102,"n":"0001"},{"t":174,"c":103,"n":"0010"},{"t":176,"c":104,"n":"1001"},{"t":178,"c":105,"n":"0100"},{"t":179,"c":106,"n":"1000"},{"t":180,"c":107,"n":"0001"},{"t":181,"c":108,"n":"0010"},{"t":183,"c":109,"n":"0010"},{"t":184,"c":110,"n":"0100"},{"t":185,"c":111,"n":"1000"},{"t":186,"c":112,"n":"1010"},{"t":188,"c":113,"n":"1001"},{"t":190,"c":114,"n":"0010"},{"t":190.5,"c":115,"n":"1000"},{"t":192,"c":116,"n":"0001"},{"t":192.5,"c":117,"n":"0010"},{"t":194,"c":118,"n":"0100"},{"t":194.5,"c":119,"n":"1000"},{"t":196,"c":120,"n":"0001"},{"t":196.5,"c":121,"n":"0100"},{"t":198,"c":122,"n":"0010"},{"t":199.5,"c":123,"n":"1010"},{"t":201,"c":124,"n":"0101"},{"t":202.5,"c":125,"n":"0011"},{"t":204,"c":126,"n":"1100"},{"t":205,"c":127,"n":"1001"},{"t":206,"c":128,"n":"0100"},{"t":206.5,"c":129,"n":"0010"},{"t":208,"c":130,"n":"0001"},{"t":209,"c":131,"n":"1001"},{"t":210,"c":132,"n":"0100"},{"t":210.5,"c":133,"n":"0010"},{"t":212,"c":134,"n":"1000"},{"t":213,"c":135,"n":"1001"},{"t":214,"c":136,"n":"0100"},{"t":215.5,"c":137,"n":"0011"},{"t":217,"c":138,"n":"1100"},{"t":218.5,"c":139,"n":"1010"},{"t":220,"c":140,"n":"0101"},{"t":221,"c":141,"n":"1001"},{"t":222,"c":142,"b":75.419},{"t":222,"c":142,"n":"0020"},{"t":223,"c":143,"n":"0032"},{"t":224,"c":144,"n":"0203"},{"t":225,"c":145,"n":"2300"},{"t":226,"c":146,"n":"3100"},{"t":227,"c":147,"n":"0020"},{"t":228,"c":148,"n":"2030"},{"t":229,"c":149,"n":"3200"},{"t":230,"c":150,"n":"0302"},{"t":231,"c":151,"n":"0103"},{"t":232,"c":152,"n":"0010"},{"t":232.875,"c":153,"n":"0001"},{"t":233.625,"c":154,"n":"1000"},{"t":234,"c":155,"b":78.603},{"t":234,"c":155,"n":"0100"},{"t":234.875,"c":156,"n":"0001"},{"t":235.625,"c":157,"n":"1000"},{"t":236,"c":158,"b":128.878},{"t":236,"c":158,"n":"0010"},{"t":237.625,"c":159,"n":"0001"},{"t":238.875,"c":160,"n":"1000"},{"t":240,"c":161,"n":"0010"},{"t":240.875,"c":162,"n":"0100"},{"t":241.625,"c":163,"n":"1000"},{"t":242,"c":164,"b":168.75},{"t":243.875,"c":164,"n":"0001"},{"t":246.25,"c":165,"n":"0100"},{"t":246.75,"c":166,"n":"0010"},{"t":248,"c":167,"b":216.867},{"t":249.25,"c":167,"n":"1010"},{"t":250.75,"c":168,"n":"0101"},{"t":252,"c":169,"b":274.047},{"t":252,"c":169,"n":"0010"},{"t":254,"c":170,"n":"0100"},{"t":256,"c":171,"n":"0001"},{"t":257,"c":172,"n":"0100"},{"t":258,"c":173,"n":"0001"},{"t":259,"c":174,"n":"1000"},{"t":261,"c":175,"n":"0100"},{"t":262,"c":176,"n":"0010"},{"t":263,"c":177,"n":"0001"},{"t":265,"c":178,"n":"1000"},{"t":267,"c":179,"n":"1000"},{"t":268,"c":180,"n":"0100"},{"t":270,"c":181,"n":"1001"},{"t":273.25,"c":182,"n":"0010"},{"t":274.5,"c":183,"n":"0010"},{"t":276,"c":184,"n":"0001"},{"t":277,"c":185,"n":"0100"},{"t":278,"c":186,"n":"0010"},{"t":279,"c":187,"n":"1000"},{"t":280,"c":188,"n":"0100"},{"t":282,"c":189,"n":"1001"},{"t":284,"c":190,"n":"0110"},{"t":285.5,"c":191,"n":"0010"},{"t":287,"c":192,"n":"1000"},{"t":288,"c":193,"n":"0110"},{"t":289.5,"c":194,"n":"0010"},{"t":291,"c":195,"n":"0001"},{"t":292,"c":196,"n":"0110"},{"t":293.5,"c":197,"n":"1000"},{"t":295,"c":198,"n":"0100"},{"t":296,"c":199,"n":"0110"},{"t":297.5,"c":200,"n":"0001"},{"t":299,"c":201,"n":"0100"},{"t":300,"c":202,"n":"0010"},{"t":300.5,"c":203,"n":"1000"},{"t":302,"c":204,"n":"0100"},{"t":302.5,"c":205,"n":"0001"},{"t":304,"c":206,"n":"0010"},{"t":304.5,"c":207,"n":"0001"},{"t":306,"c":208,"n":"0100"},{"t":306.5,"c":209,"n":"1000"},{"t":308,"c":210,"n":"0010"},{"t":309,"c":211,"n":"0001"},{"t":310,"c":212,"n":"0010"},{"t":311,"c":213,"n":"0100"},{"t":312,"c":214,"n":"0010"},{"t":313,"c":215,"n":"1000"},{"t":314,"c":216,"n":"0010"},{"t":315,"c":217,"n":"0001"},{"t":316,"c":218,"n":"0100"},{"t":317,"c":219,"n":"0001"},{"t":318,"c":220,"n":"0100"},{"t":319,"c":221,"n":"0010"},{"t":320,"c":222,"n":"0100"},{"t":321,"c":223,"n":"1000"},{"t":322,"c":224,"n":"0100"},{"t":323,"c":225,"n":"0001"},{"t":324,"c":226,"n":"1000"},{"t":325,"c":227,"n":"0010"},{"t":326,"c":228,"n":"1000"},{"t":327,"c":229,"n":"0001"},{"t":328,"c":230,"n":"0100"},{"t":329,"c":231,"n":"1000"},{"t":330,"c":232,"n":"0100"},{"t":331,"c":233,"n":"0001"},{"t":332,"c":234,"n":"0010"},{"t":333,"c":235,"n":"1000"},{"t":334,"c":236,"n":"0010"},{"t":335,"c":237,"n":"0001"},{"t":336,"c":238,"n":"0010"},{"t":337,"c":239,"n":"1000"},{"t":338,"c":240,"n":"0010"},{"t":339,"c":241,"n":"0001"},{"t":340,"c":242,"n":"0100"},{"t":341,"c":243,"n":"1000"},{"t":342,"c":244,"n":"0100"},{"t":343,"c":245,"n":"0001"},{"t":344,"c":246,"n":"0100"},{"t":345,"c":247,"n":"0010"},{"t":346,"c":248,"n":"1000"},{"t":347,"c":249,"n":"0001"},{"t":348,"c":250,"n":"0010"},{"t":349,"c":251,"n":"1000"},{"t":350,"c":252,"n":"0010"},{"t":351,"c":253,"n":"0001"},{"t":352,"c":254,"n":"0100"},{"t":353,"c":255,"n":"1000"},{"t":354,"c":256,"n":"0100"},{"t":355,"c":257,"n":"0001"},{"t":358,"c":258,"n":"2002"},{"t":359,"c":259,"b":274.311},{"t":366,"c":259,"n":"3003"}],"bpms":[{"t":0,"c":0,"b":274.809},{"t":4,"c":0,"b":273.889},{"t":54,"c":9,"b":68.702},{"t":56,"c":11,"b":136.709},{"t":62,"c":15,"b":274.025},{"t":222,"c":142,"b":75.419},{"t":234,"c":155,"b":78.603},{"t":236,"c":158,"b":128.878},{"t":242,"c":164,"b":168.75},{"t":248,"c":167,"b":216.867},{"t":252,"c":169,"b":274.047},{"t":359,"c":259,"b":274.311}],"stops":[]},"Expert":{"level":15,"combo":371,"bpmDisplay":"68.000–274.000","bpmMin":274.809,"bpmMax":274.311,"events":[{"t":0,"c":0,"b":274.809},{"t":4,"c":0,"b":273.889},{"t":38,"c":0,"n":"0100"},{"t":40,"c":1,"n":"1001"},{"t":42,"c":2,"n":"0010"},{"t":43,"c":3,"n":"1000"},{"t":44,"c":4,"n":"0001"},{"t":46,"c":5,"n":"0110"},{"t":49,"c":6,"n":"0100"},{"t":50,"c":7,"n":"0010"},{"t":52,"c":8,"n":"1001"},{"t":54,"c":9,"b":68.702},{"t":54,"c":9,"n":"0200"},{"t":55.5,"c":10,"n":"1000"},{"t":56,"c":11,"b":136.709},{"t":56.5,"c":11,"n":"0001"},{"t":58,"c":12,"n":"0010"},{"t":59.5,"c":13,"n":"1000"},{"t":61,"c":14,"n":"0301"},{"t":62,"c":15,"b":274.025},{"t":62,"c":15,"n":"1000"},{"t":63,"c":16,"n":"0100"},{"t":64,"c":17,"n":"1000"},{"t":66,"c":18,"n":"0101"},{"t":67,"c":19,"n":"0010"},{"t":68,"c":20,"n":"0100"},{"t":69,"c":21,"n":"1000"},{"t":71,"c":22,"n":"0100"},{"t":72,"c":23,"n":"0001"},{"t":73,"c":24,"n":"0010"},{"t":75,"c":25,"n":"1000"},{"t":76,"c":26,"n":"0010"},{"t":77,"c":27,"n":"0001"},{"t":78,"c":28,"n":"0100"},{"t":80,"c":29,"n":"1001"},{"t":82,"c":30,"n":"0100"},{"t":83,"c":31,"n":"0010"},{"t":84,"c":32,"n":"0001"},{"t":85,"c":33,"n":"0010"},{"t":87,"c":34,"n":"0100"},{"t":88,"c":35,"n":"1000"},{"t":89,"c":36,"n":"0001"},{"t":90,"c":37,"n":"1100"},{"t":92,"c":38,"n":"0101"},{"t":94,"c":39,"n":"0010"},{"t":94.5,"c":40,"n":"1000"},{"t":95,"c":41,"n":"0010"},{"t":96,"c":42,"n":"1100"},{"t":97,"c":43,"n":"0010"},{"t":97.5,"c":44,"n":"0001"},{"t":98,"c":45,"n":"0010"},{"t":99,"c":46,"n":"0101"},{"t":100,"c":47,"n":"0010"},{"t":100.5,"c":48,"n":"1000"},{"t":101,"c":49,"n":"0010"},{"t":102,"c":50,"n":"0100"},{"t":102.5,"c":51,"n":"0001"},{"t":103,"c":52,"n":"0100"},{"t":104,"c":53,"n":"0011"},{"t":105,"c":54,"n":"0100"},{"t":105.5,"c":55,"n":"1000"},{"t":106,"c":56,"n":"0100"},{"t":107,"c":57,"n":"1010"},{"t":108,"c":58,"n":"0100"},{"t":108.5,"c":59,"n":"0001"},{"t":109,"c":60,"n":"0100"},{"t":110,"c":61,"n":"0010"},{"t":110.5,"c":62,"n":"0100"},{"t":111,"c":63,"n":"1000"},{"t":112,"c":64,"n":"1000"},{"t":112.5,"c":65,"n":"0100"},{"t":113,"c":66,"n":"0001"},{"t":114,"c":67,"n":"0010"},{"t":114.5,"c":68,"n":"0100"},{"t":115,"c":69,"n":"0001"},{"t":116,"c":70,"n":"0001"},{"t":116.5,"c":71,"n":"0100"},{"t":117,"c":72,"n":"1000"},{"t":118,"c":73,"n":"0010"},{"t":118.5,"c":74,"n":"0100"},{"t":119.5,"c":75,"n":"0001"},{"t":120,"c":76,"n":"0010"},{"t":121,"c":77,"n":"0100"},{"t":121.5,"c":78,"n":"1000"},{"t":122.5,"c":79,"n":"0100"},{"t":123,"c":80,"n":"0010"},{"t":124,"c":81,"n":"0011"},{"t":125,"c":82,"n":"1100"},{"t":126,"c":83,"n":"0010"},{"t":126.5,"c":84,"n":"0001"},{"t":127,"c":85,"n":"0010"},{"t":127.5,"c":86,"n":"0100"},{"t":129.5,"c":87,"n":"0100"},{"t":130,"c":88,"n":"0010"},{"t":130.5,"c":89,"n":"1000"},{"t":131,"c":90,"n":"0010"},{"t":131.5,"c":91,"n":"0100"},{"t":133.5,"c":92,"n":"1000"},{"t":134,"c":93,"n":"0001"},{"t":135,"c":94,"n":"0100"},{"t":136,"c":95,"n":"0100"},{"t":137,"c":96,"n":"0001"},{"t":137.5,"c":97,"n":"1000"},{"t":138,"c":98,"n":"0001"},{"t":139,"c":99,"n":"0100"},{"t":140,"c":100,"n":"0010"},{"t":140.5,"c":101,"n":"0001"},{"t":141,"c":102,"n":"0010"},{"t":141.5,"c":103,"n":"0100"},{"t":142,"c":104,"n":"1000"},{"t":142.5,"c":105,"n":"0001"},{"t":143,"c":106,"n":"1000"},{"t":145.5,"c":107,"n":"1000"},{"t":146,"c":108,"n":"0001"},{"t":146.5,"c":109,"n":"1000"},{"t":147,"c":110,"n":"0010"},{"t":147.5,"c":111,"n":"0100"},{"t":149,"c":112,"n":"0001"},{"t":149.5,"c":113,"n":"0100"},{"t":150.5,"c":114,"n":"0100"},{"t":151,"c":115,"n":"0010"},{"t":152,"c":116,"n":"0010"},{"t":152.5,"c":117,"n":"1000"},{"t":154,"c":118,"n":"0001"},{"t":154.5,"c":119,"n":"0100"},{"t":155,"c":120,"n":"1000"},{"t":155.5,"c":121,"n":"0100"},{"t":156,"c":122,"n":"0001"},{"t":156.5,"c":123,"n":"0010"},{"t":157,"c":124,"n":"0100"},{"t":158,"c":125,"n":"0001"},{"t":159,"c":126,"n":"0100"},{"t":160,"c":127,"n":"0001"},{"t":162,"c":128,"n":"1100"},{"t":163,"c":129,"n":"0010"},{"t":164,"c":130,"n":"0100"},{"t":165,"c":131,"n":"0001"},{"t":167,"c":132,"n":"0100"},{"t":168,"c":133,"n":"1000"},{"t":169,"c":134,"n":"0010"},{"t":171,"c":135,"n":"0001"},{"t":172,"c":136,"n":"0010"},{"t":173,"c":137,"n":"1000"},{"t":174,"c":138,"n":"0100"},{"t":176,"c":139,"n":"1001"},{"t":178,"c":140,"n":"0100"},{"t":179,"c":141,"n":"0010"},{"t":180,"c":142,"n":"1000"},{"t":181,"c":143,"n":"0010"},{"t":183,"c":144,"n":"0100"},{"t":184,"c":145,"n":"0001"},{"t":185,"c":146,"n":"1000"},{"t":186,"c":147,"n":"0101"},{"t":188,"c":148,"n":"1100"},{"t":190,"c":149,"n":"0010"},{"t":190.5,"c":150,"n":"0001"},{"t":191,"c":151,"n":"0010"},{"t":192,"c":152,"n":"0001"},{"t":192.5,"c":153,"n":"0100"},{"t":193,"c":154,"n":"0001"},{"t":194,"c":155,"n":"0010"},{"t":194.5,"c":156,"n":"1000"},{"t":195,"c":157,"n":"0010"},{"t":196,"c":158,"n":"1000"},{"t":196.5,"c":159,"n":"0100"},{"t":197,"c":160,"n":"1000"},{"t":198,"c":161,"n":"0010"},{"t":198.5,"c":162,"n":"0001"},{"t":199.5,"c":163,"n":"0010"},{"t":200,"c":164,"n":"0100"},{"t":201,"c":165,"n":"0010"},{"t":201.5,"c":166,"n":"1000"},{"t":202.5,"c":167,"n":"1010"},{"t":203,"c":168,"n":"0100"},{"t":204,"c":169,"n":"0011"},{"t":205,"c":170,"n":"1100"},{"t":206,"c":171,"n":"0010"},{"t":206.5,"c":172,"n":"0100"},{"t":207,"c":173,"n":"0010"},{"t":208,"c":174,"n":"1000"},{"t":209,"c":175,"n":"1100"},{"t":210,"c":176,"n":"0010"},{"t":210.5,"c":177,"n":"0100"},{"t":211,"c":178,"n":"0010"},{"t":212,"c":179,"n":"0001"},{"t":213,"c":180,"n":"0101"},{"t":214,"c":181,"n":"0010"},{"t":215,"c":182,"n":"1000"},{"t":215.5,"c":183,"n":"0001"},{"t":216.5,"c":184,"n":"0010"},{"t":217,"c":185,"n":"0100"},{"t":218,"c":186,"n":"1000"},{"t":218.5,"c":187,"n":"0001"},{"t":220,"c":188,"n":"0110"},{"t":221,"c":189,"n":"1001"},{"t":222,"c":190,"b":75.419},{"t":222,"c":190,"n":"2000"},{"t":223,"c":191,"n":"3200"},{"t":224,"c":192,"n":"0302"},{"t":225,"c":193,"n":"0023"},{"t":226,"c":194,"n":"0031"},{"t":226.5,"c":195,"n":"0100"},{"t":227,"c":196,"n":"0002"},{"t":228,"c":197,"n":"0203"},{"t":229,"c":198,"n":"2300"},{"t":230,"c":199,"n":"3020"},{"t":231,"c":200,"n":"1030"},{"t":231.5,"c":201,"n":"0100"},{"t":232,"c":202,"n":"0010"},{"t":232.875,"c":203,"n":"1000"},{"t":233.625,"c":204,"n":"0001"},{"t":234,"c":205,"b":78.603},{"t":234,"c":205,"n":"0100"},{"t":234.875,"c":206,"n":"1000"},{"t":235.625,"c":207,"n":"0001"},{"t":236,"c":208,"b":128.878},{"t":236,"c":208,"n":"0010"},{"t":237.625,"c":209,"n":"1000"},{"t":238.875,"c":210,"n":"0001"},{"t":240,"c":211,"n":"0010"},{"t":240.875,"c":212,"n":"0100"},{"t":241.625,"c":213,"n":"0001"},{"t":242,"c":214,"b":168.75},{"t":243.875,"c":214,"n":"1000"},{"t":246.25,"c":215,"n":"0100"},{"t":246.75,"c":216,"n":"0010"},{"t":248,"c":217,"b":216.867},{"t":249.25,"c":217,"n":"0011"},{"t":250.75,"c":218,"n":"1100"},{"t":252,"c":219,"b":274.047},{"t":252,"c":219,"n":"1000"},{"t":253,"c":220,"n":"0001"},{"t":254,"c":221,"n":"0010"},{"t":256,"c":222,"n":"0110"},{"t":257,"c":223,"n":"1000"},{"t":258,"c":224,"n":"0010"},{"t":259,"c":225,"n":"0001"},{"t":261,"c":226,"n":"1000"},{"t":262,"c":227,"n":"0010"},{"t":263,"c":228,"n":"0001"},{"t":265,"c":229,"n":"0100"},{"t":266,"c":230,"n":"0010"},{"t":267,"c":231,"n":"1000"},{"t":268,"c":232,"n":"0001"},{"t":270,"c":233,"n":"1010"},{"t":272,"c":234,"n":"0100"},{"t":273.25,"c":235,"n":"0011"},{"t":274.5,"c":236,"n":"1010"},{"t":276,"c":237,"n":"0100"},{"t":277,"c":238,"n":"0001"},{"t":278,"c":239,"n":"0010"},{"t":279,"c":240,"n":"1000"},{"t":280,"c":241,"n":"0010"},{"t":282,"c":242,"n":"1001"},{"t":284,"c":243,"n":"0010"},{"t":284.5,"c":244,"n":"1000"},{"t":285.5,"c":245,"n":"1000"},{"t":286,"c":246,"n":"0010"},{"t":287,"c":247,"n":"0101"},{"t":288,"c":248,"n":"0010"},{"t":288.5,"c":249,"n":"0001"},{"t":289.5,"c":250,"n":"0001"},{"t":290,"c":251,"n":"0010"},{"t":291,"c":252,"n":"1100"},{"t":292,"c":253,"n":"0100"},{"t":292.5,"c":254,"n":"0001"},{"t":293.5,"c":255,"n":"0001"},{"t":294,"c":256,"n":"0100"},{"t":295,"c":257,"n":"1010"},{"t":296,"c":258,"n":"0100"},{"t":296.5,"c":259,"n":"1000"},{"t":297.5,"c":260,"n":"1000"},{"t":298,"c":261,"n":"0100"},{"t":299,"c":262,"n":"0011"},{"t":300,"c":263,"n":"0100"},{"t":300.5,"c":264,"n":"0010"},{"t":301,"c":265,"n":"0100"},{"t":302,"c":266,"n":"0001"},{"t":302.5,"c":267,"n":"1000"},{"t":303,"c":268,"n":"0001"},{"t":304,"c":269,"n":"0010"},{"t":304.5,"c":270,"n":"0100"},{"t":305,"c":271,"n":"0010"},{"t":306,"c":272,"n":"1000"},{"t":306.5,"c":273,"n":"0001"},{"t":307,"c":274,"n":"1000"},{"t":308,"c":275,"n":"0010"},{"t":308.5,"c":276,"n":"1000"},{"t":309,"c":277,"n":"0100"},{"t":309.5,"c":278,"n":"1000"},{"t":310,"c":279,"n":"0010"},{"t":310.5,"c":280,"n":"0001"},{"t":311,"c":281,"n":"0010"},{"t":311.5,"c":282,"n":"1000"},{"t":312,"c":283,"n":"0100"},{"t":312.5,"c":284,"n":"0001"},{"t":313,"c":285,"n":"0100"},{"t":313.5,"c":286,"n":"0010"},{"t":314,"c":287,"n":"0001"},{"t":314.5,"c":288,"n":"0100"},{"t":315,"c":289,"n":"1000"},{"t":315.5,"c":290,"n":"0100"},{"t":316,"c":291,"n":"0010"},{"t":316.5,"c":292,"n":"1000"},{"t":317,"c":293,"n":"0010"},{"t":317.5,"c":294,"n":"0001"},{"t":318,"c":295,"n":"0010"},{"t":318.5,"c":296,"n":"1000"},{"t":319,"c":297,"n":"0100"},{"t":319.5,"c":298,"n":"0001"},{"t":320,"c":299,"n":"0100"},{"t":320.5,"c":300,"n":"1000"},{"t":321,"c":301,"n":"0010"},{"t":321.5,"c":302,"n":"0001"},{"t":322,"c":303,"n":"0010"},{"t":322.5,"c":304,"n":"1000"},{"t":323,"c":305,"n":"0100"},{"t":323.5,"c":306,"n":"0001"},{"t":324,"c":307,"n":"0100"},{"t":324.5,"c":308,"n":"0010"},{"t":325,"c":309,"n":"0001"},{"t":325.5,"c":310,"n":"0100"},{"t":326,"c":311,"n":"1000"},{"t":326.5,"c":312,"n":"0100"},{"t":327,"c":313,"n":"0001"},{"t":327.5,"c":314,"n":"1000"},{"t":328,"c":315,"n":"0010"},{"t":328.5,"c":316,"n":"0100"},{"t":329,"c":317,"n":"1000"},{"t":329.5,"c":318,"n":"0100"},{"t":330,"c":319,"n":"0001"},{"t":330.5,"c":320,"n":"0010"},{"t":331,"c":321,"n":"0100"},{"t":331.5,"c":322,"n":"1000"},{"t":332,"c":323,"n":"0010"},{"t":332.5,"c":324,"n":"0100"},{"t":333,"c":325,"n":"0010"},{"t":333.5,"c":326,"n":"0001"},{"t":334,"c":327,"n":"0010"},{"t":334.5,"c":328,"n":"0100"},{"t":335,"c":329,"n":"0010"},{"t":335.5,"c":330,"n":"1000"},{"t":336,"c":331,"n":"0001"},{"t":336.5,"c":332,"n":"0100"},{"t":337,"c":333,"n":"0001"},{"t":337.5,"c":334,"n":"1000"},{"t":338,"c":335,"n":"0001"},{"t":338.5,"c":336,"n":"0010"},{"t":339,"c":337,"n":"0001"},{"t":339.5,"c":338,"n":"1000"},{"t":340,"c":339,"n":"0100"},{"t":340.5,"c":340,"n":"0010"},{"t":341,"c":341,"n":"0100"},{"t":341.5,"c":342,"n":"0001"},{"t":342,"c":343,"n":"0100"},{"t":342.5,"c":344,"n":"0010"},{"t":343,"c":345,"n":"0100"},{"t":343.5,"c":346,"n":"1000"},{"t":344,"c":347,"n":"0010"},{"t":344.5,"c":348,"n":"1000"},{"t":345,"c":349,"n":"0010"},{"t":345.5,"c":350,"n":"0100"},{"t":346,"c":351,"n":"0010"},{"t":346.5,"c":352,"n":"0001"},{"t":347,"c":353,"n":"0010"},{"t":347.5,"c":354,"n":"0100"},{"t":348,"c":355,"n":"1000"},{"t":348.5,"c":356,"n":"0100"},{"t":349,"c":357,"n":"1000"},{"t":349.5,"c":358,"n":"0001"},{"t":350,"c":359,"n":"0010"},{"t":350.5,"c":360,"n":"0001"},{"t":351,"c":361,"n":"0010"},{"t":351.5,"c":362,"n":"1000"},{"t":352,"c":363,"n":"0100"},{"t":352.5,"c":364,"n":"0010"},{"t":353,"c":365,"n":"0100"},{"t":353.5,"c":366,"n":"0001"},{"t":354,"c":367,"n":"0100"},{"t":354.5,"c":368,"n":"0010"},{"t":355,"c":369,"n":"0001"},{"t":358,"c":370,"n":"2002"},{"t":359,"c":371,"b":274.311},{"t":366,"c":371,"n":"3003"}],"bpms":[{"t":0,"c":0,"b":274.809},{"t":4,"c":0,"b":273.889},{"t":54,"c":9,"b":68.702},{"t":56,"c":11,"b":136.709},{"t":62,"c":15,"b":274.025},{"t":222,"c":190,"b":75.419},{"t":234,"c":205,"b":78.603},{"t":236,"c":208,"b":128.878},{"t":242,"c":214,"b":168.75},{"t":248,"c":217,"b":216.867},{"t":252,"c":219,"b":274.047},{"t":359,"c":371,"b":274.311}],"stops":[]},"Challenge":{"level":18,"combo":418,"bpmDisplay":"68.000–274.000","bpmMin":274.809,"bpmMax":274.311,"events":[{"t":0,"c":0,"b":274.809},{"t":4,"c":0,"b":273.889},{"t":38,"c":0,"n":"1001"},{"t":39,"c":1,"n":"0010"},{"t":40,"c":2,"n":"1100"},{"t":42,"c":3,"n":"0010"},{"t":42.5,"c":4,"n":"0001"},{"t":43,"c":5,"n":"0010"},{"t":44,"c":6,"n":"1001"},{"t":45,"c":7,"n":"0100"},{"t":46,"c":8,"n":"1010"},{"t":49,"c":9,"n":"0100"},{"t":50,"c":10,"n":"0110"},{"t":51,"c":11,"n":"1000"},{"t":52,"c":12,"n":"0101"},{"t":54,"c":13,"b":68.702},{"t":54,"c":13,"n":"0020"},{"t":55.5,"c":14,"n":"1000"},{"t":56,"c":15,"b":136.709},{"t":56.5,"c":15,"n":"0001"},{"t":58,"c":16,"n":"0100"},{"t":59.5,"c":17,"n":"1000"},{"t":61,"c":18,"n":"0031"},{"t":62,"c":19,"b":274.025},{"t":62,"c":19,"n":"1000"},{"t":62.5,"c":20,"n":"0100"},{"t":63,"c":21,"n":"1000"},{"t":64,"c":22,"n":"0011"},{"t":65,"c":23,"n":"0100"},{"t":66,"c":24,"n":"1100"},{"t":67,"c":25,"n":"0010"},{"t":67.5,"c":26,"n":"0001"},{"t":68,"c":27,"n":"1000"},{"t":69,"c":28,"n":"1001"},{"t":70,"c":29,"n":"0100"},{"t":71,"c":30,"n":"0010"},{"t":71.5,"c":31,"n":"1000"},{"t":72,"c":32,"n":"0001"},{"t":73,"c":33,"n":"1001"},{"t":74,"c":34,"n":"0010"},{"t":75,"c":35,"n":"0100"},{"t":75.5,"c":36,"n":"0010"},{"t":76,"c":37,"n":"1001"},{"t":77,"c":38,"n":"0100"},{"t":78,"c":39,"n":"0101"},{"t":79,"c":40,"n":"0010"},{"t":80,"c":41,"n":"1001"},{"t":81,"c":42,"n":"0100"},{"t":82,"c":43,"n":"0010"},{"t":82.5,"c":44,"n":"0100"},{"t":83,"c":45,"n":"0010"},{"t":84,"c":46,"n":"0101"},{"t":85,"c":47,"n":"0010"},{"t":86,"c":48,"n":"1001"},{"t":87,"c":49,"n":"0100"},{"t":87.5,"c":50,"n":"0010"},{"t":88,"c":51,"n":"0001"},{"t":89,"c":52,"n":"0100"},{"t":90,"c":53,"n":"1010"},{"t":91,"c":54,"n":"0100"},{"t":92,"c":55,"n":"1001"},{"t":93,"c":56,"n":"0010"},{"t":94,"c":57,"n":"1000"},{"t":94.5,"c":58,"n":"0100"},{"t":95,"c":59,"n":"1000"},{"t":96,"c":60,"n":"1010"},{"t":97,"c":61,"n":"0001"},{"t":97.5,"c":62,"n":"0100"},{"t":98,"c":63,"n":"0001"},{"t":99,"c":64,"n":"0011"},{"t":100,"c":65,"n":"1000"},{"t":100.5,"c":66,"n":"0001"},{"t":101,"c":67,"n":"1001"},{"t":102,"c":68,"n":"1000"},{"t":102.5,"c":69,"n":"0010"},{"t":103,"c":70,"n":"1000"},{"t":104,"c":71,"n":"1100"},{"t":105,"c":72,"n":"0001"},{"t":105.5,"c":73,"n":"0010"},{"t":106,"c":74,"n":"0001"},{"t":107,"c":75,"n":"0101"},{"t":108,"c":76,"n":"1000"},{"t":108.5,"c":77,"n":"0001"},{"t":109,"c":78,"n":"1001"},{"t":110,"c":79,"n":"1000"},{"t":110.5,"c":80,"n":"0100"},{"t":111,"c":81,"n":"1100"},{"t":112,"c":82,"n":"1000"},{"t":112.5,"c":83,"n":"0001"},{"t":113,"c":84,"n":"1001"},{"t":114,"c":85,"n":"0010"},{"t":114.5,"c":86,"n":"0001"},{"t":115,"c":87,"n":"0011"},{"t":116,"c":88,"n":"0010"},{"t":116.5,"c":89,"n":"0100"},{"t":117,"c":90,"n":"0110"},{"t":118,"c":91,"n":"1000"},{"t":118.5,"c":92,"n":"1100"},{"t":119.5,"c":93,"n":"0001"},{"t":120,"c":94,"n":"0101"},{"t":121,"c":95,"n":"0010"},{"t":121.5,"c":96,"n":"1010"},{"t":122.5,"c":97,"n":"0010"},{"t":123,"c":98,"n":"0011"},{"t":124,"c":99,"n":"0110"},{"t":125,"c":100,"n":"1001"},{"t":126,"c":101,"n":"0010"},{"t":126.5,"c":102,"n":"1000"},{"t":127,"c":103,"n":"0001"},{"t":127.5,"c":104,"n":"0101"},{"t":129.5,"c":105,"n":"0100"},{"t":130,"c":106,"n":"0010"},{"t":130.5,"c":107,"n":"0001"},{"t":131,"c":108,"n":"1000"},{"t":131.5,"c":109,"n":"1100"},{"t":133.5,"c":110,"n":"0001"},{"t":134,"c":111,"n":"1100"},{"t":135,"c":112,"n":"1001"},{"t":136,"c":113,"n":"0101"},{"t":137,"c":114,"n":"0010"},{"t":137.5,"c":115,"n":"1000"},{"t":138,"c":116,"n":"1010"},{"t":139,"c":117,"n":"1001"},{"t":140,"c":118,"n":"0100"},{"t":140.5,"c":119,"n":"0001"},{"t":141,"c":120,"n":"0100"},{"t":141.5,"c":121,"n":"0010"},{"t":142,"c":122,"n":"0100"},{"t":142.5,"c":123,"n":"1000"},{"t":143,"c":124,"n":"0110"},{"t":145.5,"c":125,"n":"0100"},{"t":146,"c":126,"n":"0010"},{"t":146.5,"c":127,"n":"1000"},{"t":147,"c":128,"n":"0100"},{"t":147.5,"c":129,"n":"0001"},{"t":149,"c":130,"n":"0001"},{"t":149.5,"c":131,"n":"0101"},{"t":150.5,"c":132,"n":"0010"},{"t":151,"c":133,"n":"1010"},{"t":152,"c":134,"n":"0100"},{"t":152.5,"c":135,"n":"0110"},{"t":154,"c":136,"n":"0001"},{"t":154.5,"c":137,"n":"0100"},{"t":155,"c":138,"n":"0010"},{"t":155.5,"c":139,"n":"1000"},{"t":156,"c":140,"n":"0100"},{"t":156.5,"c":141,"n":"0010"},{"t":157,"c":142,"n":"1001"},{"t":158,"c":143,"n":"1000"},{"t":158.5,"c":144,"n":"0100"},{"t":159,"c":145,"n":"1000"},{"t":160,"c":146,"n":"0011"},{"t":161,"c":147,"n":"0100"},{"t":162,"c":148,"n":"1100"},{"t":163,"c":149,"n":"0010"},{"t":163.5,"c":150,"n":"0001"},{"t":164,"c":151,"n":"1000"},{"t":165,"c":152,"n":"1001"},{"t":166,"c":153,"n":"0100"},{"t":167,"c":154,"n":"0010"},{"t":167.5,"c":155,"n":"1000"},{"t":168,"c":156,"n":"0001"},{"t":169,"c":157,"n":"1001"},{"t":170,"c":158,"n":"0010"},{"t":171,"c":159,"n":"0100"},{"t":171.5,"c":160,"n":"0010"},{"t":172,"c":161,"n":"1001"},{"t":173,"c":162,"n":"0100"},{"t":174,"c":163,"n":"0101"},{"t":175,"c":164,"n":"0010"},{"t":176,"c":165,"n":"1001"},{"t":177,"c":166,"n":"0100"},{"t":178,"c":167,"n":"0010"},{"t":178.5,"c":168,"n":"0100"},{"t":179,"c":169,"n":"0010"},{"t":180,"c":170,"n":"0101"},{"t":181,"c":171,"n":"0010"},{"t":182,"c":172,"n":"1001"},{"t":183,"c":173,"n":"0100"},{"t":183.5,"c":174,"n":"0010"},{"t":184,"c":175,"n":"0001"},{"t":185,"c":176,"n":"0100"},{"t":186,"c":177,"n":"1010"},{"t":187,"c":178,"n":"0100"},{"t":188,"c":179,"n":"1001"},{"t":189,"c":180,"n":"0010"},{"t":190,"c":181,"n":"0100"},{"t":190.5,"c":182,"n":"0010"},{"t":191,"c":183,"n":"1001"},{"t":192,"c":184,"n":"0010"},{"t":192.5,"c":185,"n":"0100"},{"t":193,"c":186,"n":"1001"},{"t":194,"c":187,"n":"1000"},{"t":194.5,"c":188,"n":"0001"},{"t":195,"c":189,"n":"0110"},{"t":196,"c":190,"n":"0001"},{"t":196.5,"c":191,"n":"1000"},{"t":197,"c":192,"n":"0110"},{"t":198,"c":193,"n":"0001"},{"t":198.5,"c":194,"n":"0110"},{"t":199.5,"c":195,"n":"1000"},{"t":200,"c":196,"n":"0110"},{"t":201,"c":197,"n":"0001"},{"t":201.5,"c":198,"n":"0110"},{"t":202.5,"c":199,"n":"1000"},{"t":203,"c":200,"n":"0110"},{"t":204,"c":201,"n":"1001"},{"t":204.5,"c":202,"n":"0100"},{"t":205,"c":203,"n":"1001"},{"t":206,"c":204,"n":"1010"},{"t":206.5,"c":205,"n":"0100"},{"t":207,"c":206,"n":"1001"},{"t":208,"c":207,"n":"0110"},{"t":209,"c":208,"n":"0101"},{"t":210,"c":209,"n":"0011"},{"t":210.5,"c":210,"n":"0100"},{"t":211,"c":211,"n":"1001"},{"t":212,"c":212,"n":"0110"},{"t":213,"c":213,"n":"1100"},{"t":214,"c":214,"n":"0110"},{"t":215,"c":215,"n":"0001"},{"t":215.5,"c":216,"n":"0101"},{"t":216.5,"c":217,"n":"1000"},{"t":217,"c":218,"n":"1100"},{"t":218,"c":219,"n":"0001"},{"t":218.5,"c":220,"n":"0101"},{"t":220,"c":221,"n":"1010"},{"t":220.5,"c":222,"n":"0100"},{"t":221,"c":223,"n":"1001"},{"t":222,"c":224,"b":75.419},{"t":222,"c":224,"n":"0002"},{"t":223,"c":225,"n":"0023"},{"t":224,"c":226,"n":"2030"},{"t":225,"c":227,"n":"3200"},{"t":226,"c":228,"n":"1300"},{"t":226.5,"c":229,"n":"0010"},{"t":227,"c":230,"n":"2000"},{"t":228,"c":231,"n":"3020"},{"t":229,"c":232,"n":"0032"},{"t":230,"c":233,"n":"0203"},{"t":231,"c":234,"n":"0301"},{"t":231.5,"c":235,"n":"0010"},{"t":232,"c":236,"n":"0100"},{"t":232.875,"c":237,"n":"0001"},{"t":233.625,"c":238,"n":"1000"},{"t":234,"c":239,"b":78.603},{"t":234,"c":239,"n":"0010"},{"t":234.875,"c":240,"n":"0001"},{"t":235.625,"c":241,"n":"1000"},{"t":236,"c":242,"b":128.878},{"t":236,"c":242,"n":"0100"},{"t":237.625,"c":243,"n":"0001"},{"t":238.875,"c":244,"n":"1000"},{"t":240,"c":245,"n":"0100"},{"t":240.875,"c":246,"n":"0010"},{"t":241.625,"c":247,"n":"1000"},{"t":242,"c":248,"b":168.75},{"t":243.875,"c":248,"n":"0001"},{"t":246.25,"c":249,"n":"0010"},{"t":246.75,"c":250,"n":"0100"},{"t":248,"c":251,"b":216.867},{"t":249.25,"c":251,"n":"1100"},{"t":250.75,"c":252,"n":"0011"},{"t":252,"c":253,"b":274.047},{"t":252,"c":253,"n":"1000"},{"t":252.5,"c":254,"n":"0100"},{"t":253,"c":255,"n":"1000"},{"t":254,"c":256,"n":"0011"},{"t":255,"c":257,"n":"0100"},{"t":256,"c":258,"n":"1100"},{"t":257,"c":259,"n":"0010"},{"t":257.5,"c":260,"n":"0001"},{"t":258,"c":261,"n":"1000"},{"t":259,"c":262,"n":"1001"},{"t":260,"c":263,"n":"0100"},{"t":261,"c":264,"n":"0010"},{"t":261.5,"c":265,"n":"1000"},{"t":262,"c":266,"n":"0001"},{"t":263,"c":267,"n":"1001"},{"t":264,"c":268,"n":"0010"},{"t":265,"c":269,"n":"0100"},{"t":265.5,"c":270,"n":"0010"},{"t":266,"c":271,"n":"1001"},{"t":267,"c":272,"n":"0100"},{"t":268,"c":273,"n":"0101"},{"t":269,"c":274,"n":"0010"},{"t":270,"c":275,"n":"1001"},{"t":271,"c":276,"n":"0100"},{"t":272,"c":277,"n":"1001"},{"t":273.25,"c":278,"n":"0110"},{"t":274.5,"c":279,"n":"1001"},{"t":276,"c":280,"n":"1010"},{"t":276.5,"c":281,"n":"0100"},{"t":277,"c":282,"n":"1001"},{"t":278,"c":283,"n":"0101"},{"t":278.5,"c":284,"n":"0100"},{"t":279,"c":285,"n":"1001"},{"t":280,"c":286,"n":"1000"},{"t":280.25,"c":287,"n":"0100"},{"t":282,"c":288,"n":"0001"},{"t":282.25,"c":289,"n":"0100"},{"t":284,"c":290,"n":"1000"},{"t":284.5,"c":291,"n":"1010"},{"t":285.5,"c":292,"n":"0001"},{"t":286,"c":293,"n":"0011"},{"t":287,"c":294,"n":"0110"},{"t":288,"c":295,"n":"1000"},{"t":288.5,"c":296,"n":"0100"},{"t":289.5,"c":297,"n":"0001"},{"t":290,"c":298,"n":"0100"},{"t":291,"c":299,"n":"0110"},{"t":292,"c":300,"n":"0001"},{"t":292.5,"c":301,"n":"0011"},{"t":293.5,"c":302,"n":"1000"},{"t":294,"c":303,"n":"1010"},{"t":295,"c":304,"n":"0110"},{"t":296,"c":305,"n":"0001"},{"t":296.5,"c":306,"n":"0101"},{"t":297.5,"c":307,"n":"1000"},{"t":298,"c":308,"n":"1100"},{"t":299,"c":309,"n":"0110"},{"t":300,"c":310,"n":"1001"},{"t":300.5,"c":311,"n":"0100"},{"t":301,"c":312,"n":"0101"},{"t":302,"c":313,"n":"1001"},{"t":302.5,"c":314,"n":"0100"},{"t":303,"c":315,"n":"1100"},{"t":304,"c":316,"n":"1001"},{"t":304.5,"c":317,"n":"0010"},{"t":305,"c":318,"n":"0011"},{"t":306,"c":319,"n":"1001"},{"t":306.5,"c":320,"n":"0010"},{"t":307,"c":321,"n":"1010"},{"t":308,"c":322,"n":"0100"},{"t":308.5,"c":323,"n":"1000"},{"t":309,"c":324,"n":"0010"},{"t":309.5,"c":325,"n":"1000"},{"t":310,"c":326,"n":"0100"},{"t":310.5,"c":327,"n":"0001"},{"t":311,"c":328,"n":"0100"},{"t":311.5,"c":329,"n":"1000"},{"t":312,"c":330,"n":"0010"},{"t":312.5,"c":331,"n":"0001"},{"t":313,"c":332,"n":"0010"},{"t":313.5,"c":333,"n":"0100"},{"t":314,"c":334,"n":"0001"},{"t":314.5,"c":335,"n":"0010"},{"t":315,"c":336,"n":"1000"},{"t":315.5,"c":337,"n":"0010"},{"t":316,"c":338,"n":"0100"},{"t":316.5,"c":339,"n":"1000"},{"t":317,"c":340,"n":"0100"},{"t":317.5,"c":341,"n":"0001"},{"t":318,"c":342,"n":"0100"},{"t":318.5,"c":343,"n":"1000"},{"t":319,"c":344,"n":"0010"},{"t":319.5,"c":345,"n":"0001"},{"t":320,"c":346,"n":"0010"},{"t":320.5,"c":347,"n":"1000"},{"t":321,"c":348,"n":"0100"},{"t":321.5,"c":349,"n":"0001"},{"t":322,"c":350,"n":"0100"},{"t":322.5,"c":351,"n":"1000"},{"t":323,"c":352,"n":"0010"},{"t":323.5,"c":353,"n":"0001"},{"t":324,"c":354,"n":"0010"},{"t":324.5,"c":355,"n":"0100"},{"t":325,"c":356,"n":"0001"},{"t":325.5,"c":357,"n":"0010"},{"t":326,"c":358,"n":"1000"},{"t":326.5,"c":359,"n":"0010"},{"t":327,"c":360,"n":"0001"},{"t":327.5,"c":361,"n":"1000"},{"t":328,"c":362,"n":"0100"},{"t":328.5,"c":363,"n":"0010"},{"t":329,"c":364,"n":"1000"},{"t":329.5,"c":365,"n":"0010"},{"t":330,"c":366,"n":"0001"},{"t":330.5,"c":367,"n":"0100"},{"t":331,"c":368,"n":"0010"},{"t":331.5,"c":369,"n":"1000"},{"t":332,"c":370,"n":"0100"},{"t":332.5,"c":371,"n":"0010"},{"t":333,"c":372,"n":"0100"},{"t":333.5,"c":373,"n":"0001"},{"t":334,"c":374,"n":"0100"},{"t":334.5,"c":375,"n":"0010"},{"t":335,"c":376,"n":"0100"},{"t":335.5,"c":377,"n":"1000"},{"t":336,"c":378,"n":"0001"},{"t":336.5,"c":379,"n":"0010"},{"t":337,"c":380,"n":"0001"},{"t":337.5,"c":381,"n":"1000"},{"t":338,"c":382,"n":"0001"},{"t":338.5,"c":383,"n":"0100"},{"t":339,"c":384,"n":"0001"},{"t":339.5,"c":385,"n":"1000"},{"t":340,"c":386,"n":"0010"},{"t":340.5,"c":387,"n":"0100"},{"t":341,"c":388,"n":"0010"},{"t":341.5,"c":389,"n":"0001"},{"t":342,"c":390,"n":"0010"},{"t":342.5,"c":391,"n":"0100"},{"t":343,"c":392,"n":"0010"},{"t":343.5,"c":393,"n":"1000"},{"t":344,"c":394,"n":"0100"},{"t":344.5,"c":395,"n":"1000"},{"t":345,"c":396,"n":"0100"},{"t":345.5,"c":397,"n":"0010"},{"t":346,"c":398,"n":"0100"},{"t":346.5,"c":399,"n":"0001"},{"t":347,"c":400,"n":"0100"},{"t":347.5,"c":401,"n":"0010"},{"t":348,"c":402,"n":"1000"},{"t":348.5,"c":403,"n":"0010"},{"t":349,"c":404,"n":"1000"},{"t":349.5,"c":405,"n":"0001"},{"t":350,"c":406,"n":"0100"},{"t":350.5,"c":407,"n":"0001"},{"t":351,"c":408,"n":"0100"},{"t":351.5,"c":409,"n":"1000"},{"t":352,"c":410,"n":"0010"},{"t":352.5,"c":411,"n":"0100"},{"t":353,"c":412,"n":"0010"},{"t":353.5,"c":413,"n":"0001"},{"t":354,"c":414,"n":"0010"},{"t":354.5,"c":415,"n":"0100"},{"t":355,"c":416,"n":"0001"},{"t":358,"c":417,"n":"2002"},{"t":359,"c":418,"b":274.311},{"t":366,"c":418,"n":"3003"}],"bpms":[{"t":0,"c":0,"b":274.809},{"t":4,"c":0,"b":273.889},{"t":54,"c":13,"b":68.702},{"t":56,"c":15,"b":136.709},{"t":62,"c":19,"b":274.025},{"t":222,"c":224,"b":75.419},{"t":234,"c":239,"b":78.603},{"t":236,"c":242,"b":128.878},{"t":242,"c":248,"b":168.75},{"t":248,"c":251,"b":216.867},{"t":252,"c":253,"b":274.047},{"t":359,"c":418,"b":274.311}],"stops":[]}},"title":"NGO","artist":"鍋嶋圭一"}